fits/.__init__.py.swp
fits/__init__.py
fits/fits.py
fits/header.py
fits-0.0.1.dist-info/LICENSE
fits-0.0.1.dist-info/WHEEL
fits-0.0.1.dist-info/METADATA
fits-0.0.1.dist-info/RECORD
