Metadata-Version: 2.1
Name: fits
Version: 0.0.1
Summary: FITS file loader
Keywords: FITS,Flexible Image Transport System,Astronomy
Author-email: Nicolas Tessore <n.tessore@ucl.ac.uk>
Requires-Python: >=3.8
Classifier: License :: OSI Approved :: MIT License
Project-URL: Home, https://github.com/ntessore/fits
Project-URL: Issues, https://github.com/ntessore/fits/issues
